mcl/__init__.py
mcl/sickbay/VERSION.txt
mcl/sickbay/__init__.py
mcl/sickbay/db.py
mcl/sickbay/json.py
mcl/sickbay/model/__init__.py
mcl/sickbay/model/base.py
mcl/sickbay/model/clinicalcore.py
mcl/sickbay/model/enums.py
mcl/sickbay/model/genomics.py
mcl/sickbay/model/images.py
mcl/sickbay/model/organs.py
mcl/sickbay/model/specimens.py
mcl/sickbay/tests/__init__.py
mcl.sickbay-1.2.4.dist-info/LICENSE.txt
mcl.sickbay-1.2.4.dist-info/METADATA
mcl.sickbay-1.2.4.dist-info/WHEEL
mcl.sickbay-1.2.4.dist-info/entry_points.txt
mcl.sickbay-1.2.4.dist-info/top_level.txt
mcl.sickbay-1.2.4.dist-info/zip-safe
mcl.sickbay-1.2.4.dist-info/RECORD
