Metadata-Version: 2.1
Name: mcl.sickbay
Version: 1.2.4
Summary: 🤢 Sickbay: Clinical data model for the Consortium for Molecular and Cellular Characterization of Screen-Detected Lesions.
Home-page: https://github.com/MCLConsortium/mcl.sickbay
Author: Sean Kelly
Author-email: sean.kelly@jpl.nasa.gov
License: ALv2
Keywords: rest api web clinical data lesions cancer orm model database
Classifier: Development Status :: 3 - Alpha
Classifier: Environment :: Web Environment
Classifier: Framework :: Buildout
Classifier: Intended Audience :: Developers
Classifier: Intended Audience :: Healthcare Industry
Classifier: License :: OSI Approved :: Apache Software License
Classifier: Operating System :: OS Independent
Classifier: Programming Language :: Python :: 3 :: Only
Classifier: Topic :: Database
Classifier: Topic :: Scientific/Engineering :: Bio-Informatics
License-File: LICENSE.txt
Requires-Dist: psycopg2 (==2.8.5)
Requires-Dist: sqlalchemy (==1.3.19)
Requires-Dist: aenum (==2.2.4)
